Metadata-Version: 1.0
Name: stahmctest
Version: 0.1
Summary: The funniest joke in the world
Home-page: http://github.com/storborg/funniest
Author: Flying Circus
Author-email: flyingcircus@example.com
License: DUKE
Platform: UNKNOWN
